LabelSmoothingCrossEntropy.py
helloworld.py
pytorchLosses-0.3.1.dist-info/LICENSE
pytorchLosses-0.3.1.dist-info/METADATA
pytorchLosses-0.3.1.dist-info/WHEEL
pytorchLosses-0.3.1.dist-info/top_level.txt
pytorchLosses-0.3.1.dist-info/RECORD
