Metadata-Version: 2.1
Name: pytorchLosses
Version: 0.3.1
Summary: Say hello
Home-page: https://github.com/rajanlagah/pytorch-losses.git
Author: Rajan Lagah
Author-email: rajanlagah@gmail.com
License: UNKNOWN
Platform: UNKNOWN
Classifier: Programming Language :: Python :: 3
Classifier: Programming Language :: Python :: 3.6
Classifier: Programming Language :: Python :: 3.7
Classifier: License :: OSI Approved :: GNU General Public License v2 or later (GPLv2+)
Classifier: Operating System :: OS Independent
Requires-Dist: torch (>=1.6.0)
Provides-Extra: dev
Requires-Dist: pytest (>=3.7) ; extra == 'dev'
